sysinfop/__init__.py
sysinfop/console.py
sysinfop/render.py
sysinfop/sysinfo.py
sysinfop-0.1.1.dist-info/entry_points.txt
sysinfop-0.1.1.dist-info/WHEEL
sysinfop-0.1.1.dist-info/METADATA
sysinfop-0.1.1.dist-info/RECORD
