Metadata-Version: 2.1
Name: sysinfop
Version: 0.1.1
Summary: Lightweight system info grabber
Author: Josh Burns
Author-email: joshyburnss@gmail.com
Requires-Python: >=3.11,<4.0
Classifier: Programming Language :: Python :: 3
Classifier: Programming Language :: Python :: 3.11
Requires-Dist: psutil (>=5.9.4,<6.0.0)
Requires-Dist: rich (>=12.6.0,<13.0.0)
